{
  "meta": {
    "version": "V7.0",
    "name": "话术库（成交转化高级升华版）",
    "description": "剔除了'早买早享受'等烂大街俗语，升级为'价值升华'、'场景代入'、'心理账户'等高转化话术，且严格符合合规要求",
    "last_update": "2026-01-08",
    "total_variants": 60,
    "compliance_check": "已移除所有限时/限量/促销/赠送类违规表达"
  },
  "15个营销标签体系": {
    "说明": "话术库适用人群必须使用以下15个标签",
    "身份类（5个）": [
      "老板",
      "领导",
      "懂茶的人",
      "老茶客",
      "有品位的人"
    ],
    "场景类（6个）": [
      "商务送礼的人",
      "想送礼的人",
      "办公室喝茶的人",
      "经常待客的人",
      "日常品饮的人",
      "喜欢存茶的人"
    ],
    "价值观类（4个）": [
      "注重品质的人",
      "追求性价比的人",
      "工作忙碌的人",
      "注重健康的人"
    ]
  },
  "全局禁止话术表达": {
    "说明": "🔴 同步合规库V5.0，以下表达虽不一定违规，但因过度使用或太低端而被本系统禁止",
    "烂大街俗语": [
      "早买早享受",
      "不会错的",
      "值得你拥有",
      "不可错过",
      "一定要买",
      "买它买它",
      "听我的准没错"
    ],
    "违规促销类": [
      "限时优惠",
      "今日特价",
      "最后一天",
      "前100名",
      "买一送一",
      "送赠品",
      "清仓处理",
      "亏本冲量"
    ]
  },
  "转化话术变体库": {
    "说明": "⚠️ 字段名已与N8N代码'获取结尾CTA'函数完全对齐",
    "场景化转化话术": {
      "适用场景": ["场景代入型文案", "情感共鸣型文案"],
      "设计逻辑": "将产品融入具体生活场景，激发'我也想要这种生活'的冲动",
      "变体": [
        "办公室常备一罐，累了困了泡一杯，对自己好一点。",
        "与其喝外卖奶茶，不如在办公桌上养一盆'兰花'，点击购物车带走。",
        "周末宅家，一本书一杯茶，这才是向往的生活，点击下方链接开启。",
        "家里来客人的时候，泡这杯茶，面子和里子都有了。",
        "应酬多了胃难受？常备这款茶，给身体放个假。",
        "忙碌了一整年，是时候用这杯非遗好茶，犒劳一下自己了。",
        "别让快节奏的生活，带走了你品茶的雅兴，点击下单找回初心。",
        "出差旅行带上它，无论在哪，都能喝到一口家乡味。",
        "把这盒茶放在茶几上，家里的档次瞬间就上来了。",
        "懂生活的人，杯子里总有一股兰花香，点击购买同款。"
      ]
    },
    "价值升华话术": {
      "适用场景": ["高端送礼", "老板/领导人群"],
      "设计逻辑": "不谈价格，谈价值、谈尊重、谈品位",
      "变体": [
        "送礼送的不是茶，是一份拿得出手的尊重，点击下单。",
        "这不只是一盒铁观音，更是你待客的底气，懂的入。",
        "喝茶是门学问，选这款茶，证明你是个懂行的人。",
        "为品质买单，永远比为包装买单更划算，点击购物车。",
        "好茶会说话，客户喝一口就知道你的诚意，赶紧备上。",
        "把钱花在品质上，而不是花在广告上，这就是聪明人的选择。",
        "给自己选一款能喝一辈子的口粮茶，比什么都重要。",
        "非遗传承人的手艺，值得你细细品味，点击链接支持匠心。",
        "用一顿饭钱，换来一个月的品质生活，这笔账算得过来。",
        "真正的高级，不是价格贵，而是品质对，点击购买正宗好茶。"
      ]
    },
    "信任背书话术": {
      "适用场景": ["成分党", "理性消费者"],
      "设计逻辑": "用安全感消除最后的顾虑",
      "变体": [
        "每一批都送检，报告随茶附送，闭眼入都放心。",
        "源头茶园直发，没有中间商赚差价，点击下方放心拍。",
        "老客户回购了三次的口粮茶，品质经得起考验，点击试喝。",
        "敢把检测报告印在包装上的，安溪没几家，这款可以放心入。",
        "非遗大师监制，不是贴牌货，喝进肚子里的要选正宗的。",
        "如果你懂茶，看一眼干茶就知道是好东西，现货直发。",
        "几十万茶友的选择，跟着大家买，绝对不踩雷。",
        "支持开箱验货，好品质不怕你挑剔，点击购物车。",
        "做回头客生意的茶厂，只做良心茶，赶紧下单试试。",
        "不用担心全是梗，只取四两精华，每一颗都是好茶。"
      ]
    },
    "直接指令话术": {
      "适用场景": ["促销（合规范围内）", "高性价比"],
      "设计逻辑": "简单直接，指令清晰，适合短平快的视频",
      "变体": [
        "库存不多，想喝正宗兰花香的，赶紧点击购物车。",
        "趁现在源头有货，给自己囤两盒，手慢无。",
        "不需要犹豫，这个价格喝到非遗品质，真的很难得。",
        "点击下方小黄车，今天发货，过几天就能喝上。",
        "不用比价了，源头直供就是底价，直接拍。",
        "想喝好茶别等待，点击链接，把春天带回家。",
        "与其纠结买哪家，不如试试这款老茶客都夸的。",
        "链接就在左下角，点进去看看，会有惊喜。",
        "好茶不等人，现在下单，还能赶上这批新茶。",
        "别让你的茶杯空着，点击购买，续上这杯兰花香。"
      ]
    },
    "社交送礼话术": {
      "适用场景": ["节日送礼", "商务维护"],
      "设计逻辑": "强调送礼的后果（被夸、有面子）",
      "变体": [
        "过节送礼不知道送什么？选这款，长辈夸你会办事。",
        "送领导怕出错？这款非遗监制，稳妥又有面子。",
        "一份好茶，能拉近你和客户的距离，点击下单。",
        "别再送烟酒了，送健康送文化，这款茶最合适。",
        "包装大气，品质过硬，送礼拿得出手，赶紧备两盒。",
        "让你的礼物在堆积如山的礼品中脱颖而出，选它没错。",
        "送给懂茶的朋友，他一定会问你在哪买的。",
        "不仅好喝，更显档次，商务伴手礼的首选。",
        "把心意装进礼盒，送给最重要的人，点击购买。",
        "礼轻情意重，这款茶能代表你的满满诚意。"
      ]
    }
  }
}
